prefect_pokemon/__init__.py
prefect_pokemon/_version.py
prefect_pokemon/credentials.py
prefect_pokemon/pokemon.py
prefect_pokemon-0.1.0.dist-info/LICENSE
prefect_pokemon-0.1.0.dist-info/METADATA
prefect_pokemon-0.1.0.dist-info/WHEEL
prefect_pokemon-0.1.0.dist-info/top_level.txt
prefect_pokemon-0.1.0.dist-info/RECORD
